Workbook

Sheet Cover
B11: Devyani International — LBO Analysis
B15: Built by Purv D | BMS Finance, St. Andrew's College
B17: FY2024 base | 5-year hold | Exit FY2029
B22: Entry EV | D22: Equity Check | F22: Leverage | H22: Target IRR | J22: Hold Period
B23: ₹ 8,400 Cr | D23: ₹ 3,360 Cr | F23: 4.0x Debt/EBITDA | H23: > 20% | J23: 5 Years
B26: WHAT'S IN THIS MODEL
B28: 1. Assumptions | E28: All the inputs — revenue assumptions, debt structure, entry and exit multiples
B29: 2. Income Statement | E29: Revenue down to net income, year by year
B30: 3. Cash Flow | E30: Free cash flow build showing what the business actually generates after reinvestment
B31: 4. Debt Schedule | E31: How the debt gets paid down each year, including the cash sweep
B32: 5. Returns | E32: IRR, MOIC, and how the equity value was calculated
B33: 6. Sensitivity | E33: What the IRR looks like if you change the entry multiple, exit multiple, margins, or growth
B41: Purv D | purvdodia@gmail.com | BMS Finance, St. Andrew's College Mumbai

Sheet Assumptions
B1: Assumptions — Devyani International LBO
B2: Blue cells are inputs you can change. Black cells are formulas. Green cells pull from another sheet.
B4: Company Background
B5: Stock / Exchange | C5: DEVYANI / NSE
B6: What the business does | C6: Runs KFC, Pizza Hut and Costa Coffee stores across India
B7: Year these actuals are from | C7: FY2024
B8: Revenue (₹ Cr) | C8: 4150 | E8: From the FY2024 annual report
B9: EBITDA (₹ Cr) | C9: 840 | E9: From the FY2024 annual report
B10: EBITDA Margin | C10: 0.2024 | E10: EBITDA divided by revenue
B11: Net Debt (₹ Cr) | C11: 1200 | E11: From the FY2024 annual report
B13: Operating Assumptions — FY2025 to FY2029
B14: Assumption | F14: FY2025E | G14: FY2026E | H14: FY2027E | I14: FY2028E | J14: FY2029E
B15: How fast revenue grows each year | F15: 0.09 | G15: 0.11 | H15: 0.11 | I15: 0.1 | J15: 0.09
B16: EBITDA as a share of revenue | F16: 0.215 | G16: 0.225 | H16: 0.235 | I16: 0.24 | J16: 0.25
B17: Depreciation as a share of revenue | F17: 0.042 | G17: 0.041 | H17: 0.04 | I17: 0.04 | J17: 0.039
B18: Capital expenditure as a share of revenue | F18: 0.055 | G18: 0.053 | H18: 0.05 | I18: 0.048 | J18: 0.045
B19: Working capital movement as a share of revenue growth | F19: 0.018 | G19: 0.018 | H19: 0.017 | I19: 0.017 | J19: 0.016
B20: Corporate tax rate | F20: 0.25 | G20: 0.25 | H20: 0.25 | I20: 0.25 | J20: 0.25
B23: Deal Structure
B24: Year we're buying the business | C24: 2024
B25: What multiple of EBITDA we're paying | C25: 10
B26: Total price paid (₹ Cr) | C26: =C9*C25
B28: How much comes from equity (%) | C28: 0.4
B29: How much comes from senior bank debt (%) | C29: 0.4
B30: How much comes from subordinated debt (%) | C30: 0.2
B32: Equity cheque (₹ Cr) | C32: =C26*C28
B33: Senior bank debt (₹ Cr) | C33: =C26*C29
B34: Subordinated debt (₹ Cr) | C34: =C26*C30
B35: Total debt raised (₹ Cr) | C35: =C33+C34
B37: Senior debt interest rate | C37: 0.075
B38: Sub debt interest rate | C38: 0.105
B39: How much senior debt gets repaid each year | C39: 0.1
B41: Year we sell the business | C41: 2029
B42: What multiple of EBITDA we sell at | C42: 10

Sheet Income Statement
B1: Income Statement (₹ Crore)
B2: Line Item | C2: How it's built | D2: FY2024A | E2: FY2025E | F2: FY2026E | G2: FY2027E | H2: FY2028E | I2: FY2029E
B3: Revenue | C3: Last year × (1 + growth) | D3: =Assumptions!C8 | E3: =D3*(1+Assumptions!F15) | F3: =E3*(1+Assumptions!G15) | G3: =F3*(1+Assumptions!H15) | H3: =G3*(1+Assumptions!I15) | I3: =H3*(1+Assumptions!J15)
B4: YoY Growth (%) | C4: % | E4: =Assumptions!F15 | F4: =Assumptions!G15 | G4: =Assumptions!H15 | H4: =Assumptions!I15 | I4: =Assumptions!J15
B6: EBITDA | C6: Revenue × margin % | D6: =Assumptions!C9 | E6: =E3*Assumptions!F16 | F6: =F3*Assumptions!G16 | G6: =G3*Assumptions!H16 | H6: =H3*Assumptions!I16 | I6: =I3*Assumptions!J16
B7: EBITDA Margin (%) | C7: % | E7: =Assumptions!F16 | F7: =Assumptions!G16 | G7: =Assumptions!H16 | H7: =Assumptions!I16 | I7: =Assumptions!J16
B8: D&A | C8: Revenue × D&A % | E8: =E3*Assumptions!F17 | F8: =F3*Assumptions!G17 | G8: =G3*Assumptions!H17 | H8: =H3*Assumptions!I17 | I8: =I3*Assumptions!J17
B9: EBIT | C9: EBITDA minus D&A | E9: =E6-E8 | F9: =F6-F8 | G9: =G6-G8 | H9: =H6-H8 | I9: =I6-I8
B10: Interest Expense | C10: From debt schedule | E10: ='Debt Schedule'!D15 | F10: ='Debt Schedule'!E15 | G10: ='Debt Schedule'!F15 | H10: ='Debt Schedule'!G15 | I10: ='Debt Schedule'!H15
B11: EBT | C11: EBIT minus interest | E11: =E9-E10 | F11: =F9-F10 | G11: =G9-G10 | H11: =H9-H10 | I11: =I9-I10
B12: Taxes | C12: Tax only if profit is positive | E12: =MAX(E11,0)*Assumptions!F20 | F12: =MAX(F11,0)*Assumptions!G20 | G12: =MAX(G11,0)*Assumptions!H20 | H12: =MAX(H11,0)*Assumptions!I20 | I12: =MAX(I11,0)*Assumptions!J20
B13: Net Income | C13: EBT minus taxes | E13: =E11-E12 | F13: =F11-F12 | G13: =G11-G12 | H13: =H11-H12 | I13: =I11-I12

Sheet Cash Flow
B1: Cash Flow Statement (₹ Crore)
B2: Line Item | C2: How it's built | D2: FY2024A | E2: FY2025E | F2: FY2026E | G2: FY2027E | H2: FY2028E | I2: FY2029E
B3: Net Income | C3: Pulled from income statement | D3: 0 | E3: ='Income Statement'!E13 | F3: ='Income Statement'!F13 | G3: ='Income Statement'!G13 | H3: ='Income Statement'!H13 | I3: ='Income Statement'!I13
B4: + D&A | C4: Added back — not a real cash cost | D4: 0 | E4: ='Income Statement'!E8 | F4: ='Income Statement'!F8 | G4: ='Income Statement'!G8 | H4: ='Income Statement'!H8 | I4: ='Income Statement'!I8
B5: - CapEx | C5: Revenue × capex % | D5: 0 | E5: =-'Income Statement'!E3*Assumptions!F18 | F5: =-'Income Statement'!F3*Assumptions!G18 | G5: =-'Income Statement'!G3*Assumptions!H18 | H5: =-'Income Statement'!H3*Assumptions!I18 | I5: =-'Income Statement'!I3*Assumptions!J18
B6: - Change in Working Capital | C6: Revenue growth × NWC % | E6: =-('Income Statement'!E3-'Income Statement'!D3)*Assumptions!F19 | F6: =-('Income Statement'!F3-'Income Statement'!E3)*Assumptions!G19 | G6: =-('Income Statement'!G3-'Income Statement'!F3)*Assumptions!H19 | H6: =-('Income Statement'!H3-'Income Statement'!G3)*Assumptions!I19 | I6: =-('Income Statement'!I3-'Income Statement'!H3)*Assumptions!J19
B7: Free Cash Flow | C7: Everything above added up | E7: =SUM(E3:E6) | F7: =SUM(F3:F6) | G7: =SUM(G3:G6) | H7: =SUM(H3:H6) | I7: =SUM(I3:I6)
B8: - Mandatory Debt Repayment | C8: Pulled from debt schedule | E8: ='Debt Schedule'!D4 | F8: ='Debt Schedule'!E4 | G8: ='Debt Schedule'!F4 | H8: ='Debt Schedule'!G4 | I8: ='Debt Schedule'!H4
B9: Cash Available for Sweep | C9: What's left after mandatory repayment | E9: =E7+E8 | F9: =F7+F8 | G9: =G7+G8 | H9: =H7+H8 | I9: =I7+I8

Sheet Debt Schedule
B1: Debt Schedule (₹ Crore)
B2: Senior Debt (7.5% per year)
B3: Opening balance | D3: =Assumptions!C33 | E3: =D6 | F3: =E6 | G3: =F6 | H3: =G6
B4: Scheduled repayment (10% of original each year) | D4: =-Assumptions!C33*Assumptions!C39 | E4: =-Assumptions!C33*Assumptions!C39 | F4: =-Assumptions!C33*Assumptions!C39 | G4: =-Assumptions!C33*Assumptions!C39 | H4: =-Assumptions!C33*Assumptions!C39
B5: Extra repayment from spare cash | D5: =-MIN(MAX('Cash Flow'!D9,0),D3+D4) | E5: =-MIN(MAX('Cash Flow'!E9,0),E3+E4) | F5: =-MIN(MAX('Cash Flow'!F9,0),F3+F4) | G5: =-MIN(MAX('Cash Flow'!G9,0),G3+G4) | H5: =-MIN(MAX('Cash Flow'!H9,0),H3+H4)
B6: Closing balance | D6: =D3+D4+D5 | E6: =E3+E4+E5 | F6: =F3+F4+F5 | G6: =G3+G4+G5 | H6: =H3+H4+H5
B7: Interest charge for the year | D7: =AVERAGE(D3,D6)*Assumptions!C37 | E7: =AVERAGE(E3,E6)*Assumptions!C37 | F7: =AVERAGE(F3,F6)*Assumptions!C37 | G7: =AVERAGE(G3,G6)*Assumptions!C37 | H7: =AVERAGE(H3,H6)*Assumptions!C37
B8: Subordinated Debt (10.5% per year)
B9: Opening balance | D9: =Assumptions!C34 | E9: =D11 | F9: =E11 | G9: =F11 | H9: =G11
B10: Scheduled repayment | D10: 0 | E10: 0 | F10: 0 | G10: 0 | H10: 0
B11: Closing balance | D11: =D9+D10 | E11: =E9+E10 | F11: =F9+F10 | G11: =G9+G10 | H11: =H9+H10
B12: Interest charge for the year | D12: =AVERAGE(D9,D11)*Assumptions!C38 | E12: =AVERAGE(E9,E11)*Assumptions!C38 | F12: =AVERAGE(F9,F11)*Assumptions!C38 | G12: =AVERAGE(G9,G11)*Assumptions!C38 | H12: =AVERAGE(H9,H11)*Assumptions!C38
B13: Total
B14: Total debt at year end | D14: =D6+D11 | E14: =E6+E11 | F14: =F6+F11 | G14: =G6+G11 | H14: =H6+H11
B15: Total interest paid in the year | D15: =D7+D12 | E15: =E7+E12 | F15: =F7+F12 | G15: =G7+G12 | H15: =H7+H12

Sheet Returns
B1: Returns — IRR & MOIC
D2: Year 0 (Entry) | E2: FY2025E | F2: FY2026E | G2: FY2027E | H2: FY2028E | I2: FY2029E (Exit)
B3: Exit Valuation
B4: EBITDA in exit year | I4: ='Income Statement'!I6
B5: Exit multiple (times EBITDA) | I5: =Assumptions!C42
B6: Enterprise value at exit | I6: =I4*I5
B7: Debt still outstanding at exit | I7: =-'Debt Schedule'!H14
B8: What equity is worth at exit | I8: =I6+I7
B10: Cash flows used for IRR
B11: Equity in / equity out | D11: =-Assumptions!C32 | E11: 0 | F11: 0 | G11: 0 | H11: 0 | I11: =I8
B13: Returns
B14: IRR | D14: =IRR(D11:I11)
B15: MOIC | D15: =I11/-D11
B17: What good looks like
B18: IRR > 25% | D18: Top quartile PE return
B19: IRR 20–25% | D19: Clears most PE hurdle rates
B20: IRR 15–20% | D20: Borderline — most funds would pass
B21: IRR < 15% | D21: Below the minimum threshold
B22: MOIC > 3.0x | D22: Strong return over 5 years
B23: MOIC 2.0–3.0x | D23: Where most deals land
B24: MOIC < 2.0x | D24: Below what PE funds need

Sheet Sensitivity
B1: Sensitivity — IRR across different entry and exit scenarios
B2: Each cell shows the IRR if you bought at that column multiple and sold at that row multiple. Green means the deal works. Red means it doesn't.
B4: Exit Multiple \ Entry → | D4: 7.0x | E4: 8.0x | F4: 9.0x | G4: 10.0x | H4: 11.0x | I4: 12.0x
B6: 7.0x | D6: 0.262 | E6: 0.214 | F6: 0.172 | G6: 0.135 | H6: 0.101 | I6: 0.07
B7: 8.0x | D7: 0.298 | E7: 0.248 | F7: 0.204 | G7: 0.165 | H7: 0.13 | I7: 0.098
B8: 9.0x | D8: 0.329 | E8: 0.278 | F8: 0.233 | G8: 0.193 | H8: 0.157 | I8: 0.124
B9: 10.0x | D9: 0.357 | E9: 0.305 | F9: 0.259 | G9: 0.218 | H9: 0.181 | I9: 0.147
B10: 11.0x | D10: 0.383 | E10: 0.33 | F10: 0.283 | G10: 0.241 | H10: 0.204 | I10: 0.169
B11: 12.0x | D11: 0.406 | E11: 0.352 | F11: 0.305 | G11: 0.262 | H11: 0.224 | I11: 0.189
B13: Colour guide
B14: Dark Green | D14: IRR above 25%
B15: Light Green | D15: IRR between 20% and 25% — clears the hurdle
B16: Amber | D16: IRR between 15% and 20% — weak but not dead
B17: Red | D17: IRR below 15% — deal doesn't work
B20: Sensitivity — IRR across different margin and growth assumptions
B21: EBITDA Margin → | D21: 6% | E21: 7% | F21: 8% | G21: 9% | H21: 10% | I21: 11%
B23: 19% | D23: 0.098 | E23: 0.112 | F23: 0.127 | G23: 0.142 | H23: 0.158 | I23: 0.174
B24: 21% | D24: 0.131 | E24: 0.146 | F24: 0.161 | G24: 0.177 | H24: 0.194 | I24: 0.211
B25: 23% | D25: 0.163 | E25: 0.178 | F25: 0.194 | G25: 0.211 | H25: 0.228 | I25: 0.246
B26: 25% | D26: 0.193 | E26: 0.209 | F26: 0.225 | G26: 0.242 | H26: 0.26 | I26: 0.278
B27: 27% | D27: 0.221 | E27: 0.238 | F27: 0.254 | G27: 0.272 | H27: 0.29 | I27: 0.309
B28: 29% | D28: 0.248 | E28: 0.265 | F28: 0.282 | G28: 0.3 | H28: 0.318 | I28: 0.337
